mahdi/__init__.py
mahdi/mmex.py
MAHDI_DND-5.7.dist-info/LICENSE
MAHDI_DND-5.7.dist-info/METADATA
MAHDI_DND-5.7.dist-info/WHEEL
MAHDI_DND-5.7.dist-info/top_level.txt
MAHDI_DND-5.7.dist-info/RECORD
