Metadata-Version: 2.1
Name: MAHDI-DND
Version: 5.7
Summary: this is a simple pip modul and test
License-File: LICENSE
